yt_ts_to_srt/__init__.py
yt_ts_to_srt/main.py
yt_ts_to_srt-0.0.1.dist-info/METADATA
yt_ts_to_srt-0.0.1.dist-info/WHEEL
yt_ts_to_srt-0.0.1.dist-info/entry_points.txt
yt_ts_to_srt-0.0.1.dist-info/top_level.txt
yt_ts_to_srt-0.0.1.dist-info/RECORD
