Metadata-Version: 2.4
Name: yt-ts-to-srt
Version: 0.0.1
Summary: A simple tool to convert YouTube video transcripts from JSON format to SRT subtitle files.
Author-email: Your Name <you@example.com>
Project-URL: Homepage, https://github.com/your-username/yt-ts-to-srt
Project-URL: Bug Tracker, https://github.com/your-username/yt-ts-to-srt/issues
Classifier: Programming Language :: Python :: 3
Classifier: License :: OSI Approved :: MIT License
Classifier: Operating System :: OS Independent
Requires-Python: >=3.7
